remediation/__init__.py
remediation/cli.py
remediation/remediation.py
remediation/data_generators/__init__.py
remediation/data_generators/cm11_generator.py
remediation/utils/__init__.py
remediation/utils/singleton.py
remediation-0.1.0.dist-info/AUTHORS.rst
remediation-0.1.0.dist-info/LICENSE
remediation-0.1.0.dist-info/METADATA
remediation-0.1.0.dist-info/WHEEL
remediation-0.1.0.dist-info/entry_points.txt
remediation-0.1.0.dist-info/top_level.txt
remediation-0.1.0.dist-info/RECORD
