Metadata-Version: 2.1
Name: remediation
Version: 0.1.0
Summary: Tools to support the remediation tasks, reporting and monitoring
Home-page: https://github.com/xmarlem/remediation
Author: Marco Lembo
Author-email: inglembomarco@gmail.com
License: MIT license
Keywords: remediation
Platform: UNKNOWN
Classifier: Development Status :: 2 - Pre-Alpha
Classifier: Intended Audience :: Developers
Classifier: License :: OSI Approved :: MIT License
Classifier: Natural Language :: English
Classifier: Programming Language :: Python :: 3
Classifier: Programming Language :: Python :: 3.5
Classifier: Programming Language :: Python :: 3.6
Classifier: Programming Language :: Python :: 3.7
Classifier: Programming Language :: Python :: 3.8
Requires-Python: >=3.5
